algopract/__init__.py
algopract/core/__init__.py
algopract/core/profiler.py
algopract/core/result.py
algopract/data_structures/__init__.py
algopract/data_structures/queue.py
algopract/data_structures/stack.py
algopract/graphs/__init__.py
algopract/graphs/bfs.py
algopract/graphs/dfs.py
algopract/searching/__init__.py
algopract/searching/binary_search.py
algopract/searching/interpolation_search.py
algopract/searching/jump_search.py
algopract/searching/linear_search.py
algopract/sorting/__init__.py
algopract/sorting/bubble_sort.py
algopract/sorting/insertion_sort.py
algopract/sorting/merge_sort.py
algopract/sorting/quick_sort.py
algopract/sorting/selection_sort.py
algopract-0.1.0.dist-info/licenses/LICENSE
tests/__init__.py
tests/data_structures/__init__.py
tests/data_structures/test_queue.py
tests/data_structures/test_stack.py
tests/graphs/test_bfs.py
tests/graphs/test_dfs.py
tests/searching/__init__.py
tests/searching/test_binary_search.py
tests/searching/test_interpolation_search.py
tests/searching/test_jump_search.py
tests/searching/test_linear_search.py
tests/sorting/__init__.py
tests/sorting/test_bubble_sort.py
tests/sorting/test_insertion_sort.py
tests/sorting/test_merge_sort.py
tests/sorting/test_quick_sort.py
tests/sorting/test_selection_sort.py
algopract-0.1.0.dist-info/METADATA
algopract-0.1.0.dist-info/WHEEL
algopract-0.1.0.dist-info/top_level.txt
algopract-0.1.0.dist-info/RECORD
