Metadata-Version: 2.4
Name: algopract
Version: 0.1.0
Summary: A learning-focused Python package implementing core algorithms with step-by-step explanations.
Author-email: Loka Ram Kalyan Are <alrk6125@gmail.com>
License: MIT
Requires-Python: >=3.8
License-File: LICENSE
Dynamic: license-file
